gpuview/__init__.py
gpuview/__main__.py
gpuview/app.py
gpuview/core.py
gpuview/service.sh
gpuview/test_gpuview.py
gpuview/utils.py
gpuview/views/index.tpl
gpuview-0.4.0.dist-info/LICENSE
gpuview-0.4.0.dist-info/METADATA
gpuview-0.4.0.dist-info/WHEEL
gpuview-0.4.0.dist-info/entry_points.txt
gpuview-0.4.0.dist-info/top_level.txt
gpuview-0.4.0.dist-info/zip-safe
gpuview-0.4.0.dist-info/RECORD
