Metadata-Version: 2.1
Name: gpuview
Version: 0.4.0
Summary: A lightweight web dashboard for monitoring GPU usage
Home-page: https://github.com/fgaim/gpuview
Author: Fitsum Gaim
Author-email: fitsum@geezlab.com
License: MIT
Keywords: gpu web-monitoring
Platform: UNKNOWN
Classifier: Development Status :: 3 - Alpha
Classifier: License :: OSI Approved :: MIT License
Classifier: Operating System :: POSIX :: Linux
Classifier: Programming Language :: Python :: 2.7
Classifier: Programming Language :: Python :: 3
Classifier: Topic :: System :: Monitoring
Requires-Dist: gpustat (>=0.5.0)
Requires-Dist: bottle (>=0.12.14)
Provides-Extra: test
Requires-Dist: pytest ; extra == 'test'
